fabricatio_digest/__init__.py
fabricatio_digest/config.py
fabricatio_digest/py.typed
fabricatio_digest/actions/__init__.py
fabricatio_digest/capabilities/__init__.py
fabricatio_digest/capabilities/digest.py
fabricatio_digest/models/__init__.py
fabricatio_digest/models/tasklist.py
fabricatio_digest/workflows/__init__.py
tests/test_digest.py
fabricatio_digest-0.3.0.dist-info/METADATA
fabricatio_digest-0.3.0.dist-info/WHEEL
fabricatio_digest-0.3.0.dist-info/licenses/LICENSE
fabricatio_digest-0.3.0.dist-info/RECORD
